[
  {
    "_id": "prd_t2epbbm4yg",
    "nombre": "Café de origen Huila 500g",
    "categoria_id": "cat_8v5rni5fc2",
    "marca": "Juan Valdez",
    "precio": {
      "valor": 40.52,
      "moneda": "COP"
    },
    "stock": 177,
    "descripcion": "Disponible en varias tallas y colores. Perfecto para regalo o colección.",
    "especificaciones": {
      "origen": "Alimentos",
      "color": "rojo",
      "talla": "L",
      "peso_kg": 1.54
    },
    "imagenes": [
      "https://img.ejemplo.com/img_y13vf7.jpg"
    ],
    "rating_promedio": 0.0,
    "num_resenas": 0,
    "tags": [
      "oferta",
      "regional"
    ],
    "fecha_creacion": "2023-12-07",
    "activo": true
  },
  {
    "_id": "prd_8o8w23qpge",
    "nombre": "Café de Sierra Nevada 340g",
    "categoria_id": "cat_8v5rni5fc2",
    "marca": "Tostao",
    "precio": {
      "valor": 64.13,
      "moneda": "COP"
    },
    "stock": 50,
    "descripcion": "Producto original con excelente calidad. Ideal para uso diario y recomendado por compradores.",
    "especificaciones": {
      "origen": "Hecho en Colombia",
      "color": "azul",
      "talla": "M",
      "peso_kg": 3.71
    },
    "imagenes": [
      "https://img.ejemplo.com/img_6mrizw.jpg",
      "https://img.ejemplo.com/img_b5ngj6.jpg"
    ],
    "rating_promedio": 0.0,
    "num_resenas": 0,
    "tags": [
      "regional",
      "bestseller",
      "oferta"
    ],
    "fecha_creacion": "2025-08-21",
    "activo": true
  },
  {
    "_id": "prd_dcr3v1t8hg",
    "nombre": "Arepa boyacense x10",
    "categoria_id": "cat_8v5rni5fc2",
    "marca": "La Reina",
    "precio": {
      "valor": 281.89,
      "moneda": "COP"
    },
    "stock": 236,
    "descripcion": "Disponible en varias tallas y colores. Producto original con excelente calidad.",
    "especificaciones": {
      "origen": "Importado",
      "color": null,
      "talla": "S",
      "peso_kg": 2.09
    },
    "imagenes": [
      "https://img.ejemplo.com/img_0z5kmx.jpg",
      "https://img.ejemplo.com/img_fhclk7.jpg",
      "https://img.ejemplo.com/img_gvltls.jpg"
    ],
    "rating_promedio": 0.0,
    "num_resenas": 0,
    "tags": [
      "oferta"
    ],
    "fecha_creacion": "2022-03-14",
    "activo": true
  },
  {
    "_id": "prd_p72h5gh3i6",
    "nombre": "Panela orgánica 1kg",
    "categoria_id": "cat_8v5rni5fc2",
    "marca": "Doña Panela",
    "precio": {
      "valor": 257.01,
      "moneda": "COP"
    },
    "stock": 251,
    "descripcion": "Producto original con excelente calidad. Perfecto para regalo o colección.",
    "especificaciones": {
      "origen": "Alimentos",
      "color": "azul",
      "talla": "M",
      "peso_kg": 0.6
    },
    "imagenes": [
      "https://img.ejemplo.com/img_04g4kv.jpg"
    ],
    "rating_promedio": 5.0,
    "num_resenas": 1,
    "tags": [
      "bestseller"
    ],
    "fecha_creacion": "2024-08-28",
    "activo": true
  },
  {
    "_id": "prd_o5fx45ihau",
    "nombre": "Chocolatina Jet caja surtida",
    "categoria_id": "cat_8v5rni5fc2",
    "marca": "Jet",
    "precio": {
      "valor": 33.95,
      "moneda": "COP"
    },
    "stock": 152,
    "descripcion": "Producto original con excelente calidad. Disponible en varias tallas y colores.",
    "especificaciones": {
      "origen": "Alimentos",
      "color": null,
      "talla": "S",
      "peso_kg": 0.51
    },
    "imagenes": [
      "https://img.ejemplo.com/img_mbi2ub.jpg",
      "https://img.ejemplo.com/img_rsmed5.jpg",
      "https://img.ejemplo.com/img_2z1vx3.jpg"
    ],
    "rating_promedio": 5.0,
    "num_resenas": 2,
    "tags": [
      "nuevo",
      "bestseller",
      "oferta"
    ],
    "fecha_creacion": "2022-12-18",
    "activo": true
  },
  {
    "_id": "prd_3wolab9hcw",
    "nombre": "Bocadillo veleño 400g",
    "categoria_id": "cat_8v5rni5fc2",
    "marca": "Vélez",
    "precio": {
      "valor": 103.95,
      "moneda": "COP"
    },
    "stock": 231,
    "descripcion": "Perfecto para regalo o colección. Material resistente y acabado premium.",
    "especificaciones": {
      "origen": "Importado",
      "color": "negro",
      "talla": "XS",
      "peso_kg": 0.16
    },
    "imagenes": [
      "https://img.ejemplo.com/img_ux8r4z.jpg",
      "https://img.ejemplo.com/img_x72k7j.jpg",
      "https://img.ejemplo.com/img_gnp6k0.jpg"
    ],
    "rating_promedio": 5.0,
    "num_resenas": 1,
    "tags": [
      "artesanal"
    ],
    "fecha_creacion": "2022-04-27",
    "activo": true
  },
  {
    "_id": "prd_ukoa1nsr18",
    "nombre": "Mochila Wayuu artesanal",
    "categoria_id": "cat_a7pf17yp91",
    "marca": "Artesanías Guajira",
    "precio": {
      "valor": 687.28,
      "moneda": "COP"
    },
    "stock": 204,
    "descripcion": "Perfecto para regalo o colección. Producto original con excelente calidad.",
    "especificaciones": {
      "origen": "Hecho en Colombia",
      "color": "beige",
      "talla": "M",
      "peso_kg": 0.57
    },
    "imagenes": [
      "https://img.ejemplo.com/img_by6arm.jpg",
      "https://img.ejemplo.com/img_le4s09.jpg"
    ],
    "rating_promedio": 0.0,
    "num_resenas": 0,
    "tags": [
      "regional",
      "oferta"
    ],
    "fecha_creacion": "2025-08-05",
    "activo": true
  },
  {
    "_id": "prd_jn6fqnh4hz",
    "nombre": "Sombrero vueltiao auténtico",
    "categoria_id": "cat_a7pf17yp91",
    "marca": "Zenú",
    "precio": {
      "valor": 400.88,
      "moneda": "COP"
    },
    "stock": 54,
    "descripcion": "Artesanía hecha a mano por comunidades locales. Producto original con excelente calidad.",
    "especificaciones": {
      "origen": "Hecho en Colombia",
      "color": "verde",
      "talla": "L",
      "peso_kg": 2.43
    },
    "imagenes": [
      "https://img.ejemplo.com/img_ojk5og.jpg",
      "https://img.ejemplo.com/img_ww27px.jpg"
    ],
    "rating_promedio": 5.0,
    "num_resenas": 2,
    "tags": [
      "artesanal",
      "regional",
      "bestseller"
    ],
    "fecha_creacion": "2023-09-20",
    "activo": true
  },
  {
    "_id": "prd_b29co0vs85",
    "nombre": "Ruana de lana boyacense",
    "categoria_id": "cat_a7pf17yp91",
    "marca": "Artesanías Boyacá",
    "precio": {
      "valor": 457.46,
      "moneda": "COP"
    },
    "stock": 55,
    "descripcion": "Envío rápido y empaque seguro. Perfecto para regalo o colección.",
    "especificaciones": {
      "origen": "Moda",
      "color": "azul",
      "talla": "XL",
      "peso_kg": 5.93
    },
    "imagenes": [
      "https://img.ejemplo.com/img_kmg1om.jpg",
      "https://img.ejemplo.com/img_us4pod.jpg",
      "https://img.ejemplo.com/img_gi7vuy.jpg"
    ],
    "rating_promedio": 5.0,
    "num_resenas": 3,
    "tags": [
      "regional"
    ],
    "fecha_creacion": "2022-01-31",
    "activo": true
  },
  {
    "_id": "prd_u8f32xpuai",
    "nombre": "Hamaca San Jacinto",
    "categoria_id": "cat_wblre8nf3e",
    "marca": "San Jacinto",
    "precio": {
      "valor": 591.11,
      "moneda": "COP"
    },
    "stock": 19,
    "descripcion": "Perfecto para regalo o colección. Ideal para uso diario y recomendado por compradores.",
    "especificaciones": {
      "origen": "Hogar y Cocina",
      "color": "azul",
      "talla": "L",
      "peso_kg": 3.06
    },
    "imagenes": [
      "https://img.ejemplo.com/img_olfs99.jpg",
      "https://img.ejemplo.com/img_7p39r7.jpg"
    ],
    "rating_promedio": 0.0,
    "num_resenas": 0,
    "tags": [
      "artesanal",
      "regional"
    ],
    "fecha_creacion": "2022-07-23",
    "activo": true
  },
  {
    "_id": "prd_gpvrplbk1d",
    "nombre": "Olla a presión Imusa 6L",
    "categoria_id": "cat_wblre8nf3e",
    "marca": "Imusa",
    "precio": {
      "valor": 764.17,
      "moneda": "COP"
    },
    "stock": 83,
    "descripcion": "Envío rápido y empaque seguro. Sabor tradicional colombiano y frescura garantizada.",
    "especificaciones": {
      "origen": "Importado",
      "color": "negro",
      "talla": null,
      "peso_kg": 0.93
    },
    "imagenes": [
      "https://img.ejemplo.com/img_74m8tt.jpg",
      "https://img.ejemplo.com/img_wwsy06.jpg"
    ],
    "rating_promedio": 4.5,
    "num_resenas": 2,
    "tags": [
      "oferta",
      "regional",
      "nuevo"
    ],
    "fecha_creacion": "2023-12-11",
    "activo": true
  },
  {
    "_id": "prd_pjmlozn7aa",
    "nombre": "Salsa de ají artesanal",
    "categoria_id": "cat_8v5rni5fc2",
    "marca": "El Paisa",
    "precio": {
      "valor": 118.42,
      "moneda": "COP"
    },
    "stock": 14,
    "descripcion": "Perfecto para regalo o colección. Material resistente y acabado premium.",
    "especificaciones": {
      "origen": "Hecho en Colombia",
      "color": "beige",
      "talla": "XL",
      "peso_kg": 1.25
    },
    "imagenes": [
      "https://img.ejemplo.com/img_kyk2gu.jpg"
    ],
    "rating_promedio": 5.0,
    "num_resenas": 1,
    "tags": [
      "artesanal",
      "oferta"
    ],
    "fecha_creacion": "2024-07-23",
    "activo": true
  },
  {
    "_id": "prd_6prnfapofx",
    "nombre": "Chorizo santarrosano 500g",
    "categoria_id": "cat_8v5rni5fc2",
    "marca": "Santa Rosa",
    "precio": {
      "valor": 172.4,
      "moneda": "COP"
    },
    "stock": 207,
    "descripcion": "Perfecto para regalo o colección. Ideal para uso diario y recomendado por compradores.",
    "especificaciones": {
      "origen": "Importado",
      "color": "beige",
      "talla": null,
      "peso_kg": 2.35
    },
    "imagenes": [
      "https://img.ejemplo.com/img_48pi7q.jpg"
    ],
    "rating_promedio": 5.0,
    "num_resenas": 1,
    "tags": [
      "bestseller",
      "nuevo",
      "regional"
    ],
    "fecha_creacion": "2024-10-08",
    "activo": true
  },
  {
    "_id": "prd_eryhusb8tn",
    "nombre": "Queso costeño 1kg",
    "categoria_id": "cat_8v5rni5fc2",
    "marca": "Alpina",
    "precio": {
      "valor": 232.78,
      "moneda": "COP"
    },
    "stock": 238,
    "descripcion": "Perfecto para regalo o colección. Sabor tradicional colombiano y frescura garantizada.",
    "especificaciones": {
      "origen": "Importado",
      "color": "rojo",
      "talla": "S",
      "peso_kg": 2.96
    },
    "imagenes": [
      "https://img.ejemplo.com/img_nn40k7.jpg",
      "https://img.ejemplo.com/img_vqsb1e.jpg",
      "https://img.ejemplo.com/img_0rm70w.jpg"
    ],
    "rating_promedio": 4.0,
    "num_resenas": 1,
    "tags": [
      "oferta"
    ],
    "fecha_creacion": "2024-05-22",
    "activo": true
  },
  {
    "_id": "prd_sn4owuhs2i",
    "nombre": "Kit de aromáticas colombianas",
    "categoria_id": "cat_8v5rni5fc2",
    "marca": "Hindú",
    "precio": {
      "valor": 169.61,
      "moneda": "COP"
    },
    "stock": 165,
    "descripcion": "Perfecto para regalo o colección. Disponible en varias tallas y colores.",
    "especificaciones": {
      "origen": "Importado",
      "color": "beige",
      "talla": "L",
      "peso_kg": 0.12
    },
    "imagenes": [
      "https://img.ejemplo.com/img_cxeuhq.jpg",
      "https://img.ejemplo.com/img_3sklxi.jpg"
    ],
    "rating_promedio": 0.0,
    "num_resenas": 0,
    "tags": [
      "regional"
    ],
    "fecha_creacion": "2025-06-14",
    "activo": true
  },
  {
    "_id": "prd_ew98bshuu3",
    "nombre": "Balón Golty profesional",
    "categoria_id": "cat_qtmrgb5i2h",
    "marca": "Golty",
    "precio": {
      "valor": 405.66,
      "moneda": "COP"
    },
    "stock": 130,
    "descripcion": "Artesanía hecha a mano por comunidades locales. Producto original con excelente calidad.",
    "especificaciones": {
      "origen": "Importado",
      "color": "rojo",
      "talla": "L",
      "peso_kg": 0.14
    },
    "imagenes": [
      "https://img.ejemplo.com/img_0mdlck.jpg"
    ],
    "rating_promedio": 0.0,
    "num_resenas": 0,
    "tags": [
      "artesanal",
      "bestseller"
    ],
    "fecha_creacion": "2022-05-10",
    "activo": true
  },
  {
    "_id": "prd_a49y4jixr4",
    "nombre": "Camiseta Selección Colombia",
    "categoria_id": "cat_qtmrgb5i2h",
    "marca": "Adidas",
    "precio": {
      "valor": 601.74,
      "moneda": "COP"
    },
    "stock": 116,
    "descripcion": "Disponible en varias tallas y colores. Ideal para uso diario y recomendado por compradores.",
    "especificaciones": {
      "origen": "Hecho en Colombia",
      "color": "beige",
      "talla": "S",
      "peso_kg": 1.31
    },
    "imagenes": [
      "https://img.ejemplo.com/img_jzkhdq.jpg",
      "https://img.ejemplo.com/img_r525l0.jpg"
    ],
    "rating_promedio": 4.0,
    "num_resenas": 1,
    "tags": [
      "artesanal"
    ],
    "fecha_creacion": "2023-09-25",
    "activo": true
  },
  {
    "_id": "prd_jkbxwyfwxk",
    "nombre": "Libro 'Cien años de soledad'",
    "categoria_id": "cat_n9nadz9rrt",
    "marca": "Penguin Random House",
    "precio": {
      "valor": 161.23,
      "moneda": "COP"
    },
    "stock": 171,
    "descripcion": "Artesanía hecha a mano por comunidades locales. Material resistente y acabado premium.",
    "especificaciones": {
      "origen": "Hecho en Colombia",
      "color": "negro",
      "talla": null,
      "peso_kg": 5.76
    },
    "imagenes": [
      "https://img.ejemplo.com/img_ga5j8g.jpg"
    ],
    "rating_promedio": 5.0,
    "num_resenas": 1,
    "tags": [
      "oferta",
      "regional"
    ],
    "fecha_creacion": "2025-04-11",
    "activo": true
  },
  {
    "_id": "prd_wax0a4wm43",
    "nombre": "Teclado mecánico Redragon",
    "categoria_id": "cat_ig7gpfbsxi",
    "marca": "Redragon",
    "precio": {
      "valor": 71.38,
      "moneda": "COP"
    },
    "stock": 248,
    "descripcion": "Producto original con excelente calidad. Perfecto para regalo o colección.",
    "especificaciones": {
      "origen": "Importado",
      "color": "negro",
      "talla": "M",
      "peso_kg": 3.16
    },
    "imagenes": [
      "https://img.ejemplo.com/img_l9m0na.jpg",
      "https://img.ejemplo.com/img_ymwfio.jpg",
      "https://img.ejemplo.com/img_wptdln.jpg"
    ],
    "rating_promedio": 0.0,
    "num_resenas": 0,
    "tags": [
      "artesanal"
    ],
    "fecha_creacion": "2025-11-21",
    "activo": true
  },
  {
    "_id": "prd_vhx74wabnb",
    "nombre": "Audífonos Xiaomi Redmi Buds",
    "categoria_id": "cat_fywrh23ssi",
    "marca": "Xiaomi",
    "precio": {
      "valor": 774.88,
      "moneda": "COP"
    },
    "stock": 69,
    "descripcion": "Material resistente y acabado premium. Artesanía hecha a mano por comunidades locales.",
    "especificaciones": {
      "origen": "Importado",
      "color": "rojo",
      "talla": "S",
      "peso_kg": 2.56
    },
    "imagenes": [
      "https://img.ejemplo.com/img_4ll1je.jpg",
      "https://img.ejemplo.com/img_vmvciu.jpg"
    ],
    "rating_promedio": 0.0,
    "num_resenas": 0,
    "tags": [
      "artesanal"
    ],
    "fecha_creacion": "2025-07-09",
    "activo": true
  },
  {
    "_id": "prd_ar0np1gqwu",
    "nombre": "Portátil 14'' i5 16GB 897",
    "categoria_id": "cat_ig7gpfbsxi",
    "marca": "Asus",
    "precio": {
      "valor": 615.87,
      "moneda": "COP"
    },
    "stock": 309,
    "descripcion": "Artesanía hecha a mano por comunidades locales. Sabor tradicional colombiano y frescura garantizada.",
    "especificaciones": {
      "color": "verde",
      "talla": "S",
      "peso_kg": 3.24
    },
    "imagenes": [
      "https://img.ejemplo.com/img_fc63d6.jpg",
      "https://img.ejemplo.com/img_nsslod.jpg"
    ],
    "rating_promedio": 4.5,
    "num_resenas": 2,
    "tags": [
      "eco"
    ],
    "fecha_creacion": "2024-08-27",
    "activo": true
  },
  {
    "_id": "prd_6btxmk1a1b",
    "nombre": "Portátil 14'' i5 16GB 215",
    "categoria_id": "cat_ig7gpfbsxi",
    "marca": "Asus",
    "precio": {
      "valor": 683.14,
      "moneda": "COP"
    },
    "stock": 86,
    "descripcion": "Envío rápido y empaque seguro. Producto original con excelente calidad.",
    "especificaciones": {
      "color": "gris",
      "talla": "S",
      "peso_kg": 1.47
    },
    "imagenes": [
      "https://img.ejemplo.com/img_dw0q72.jpg"
    ],
    "rating_promedio": 5.0,
    "num_resenas": 2,
    "tags": [
      "popular",
      "importado"
    ],
    "fecha_creacion": "2024-12-03",
    "activo": true
  },
  {
    "_id": "prd_p5y6c6wn7z",
    "nombre": "Zapatillas running 744",
    "categoria_id": "cat_a7pf17yp91",
    "marca": "Nike",
    "precio": {
      "valor": 212.15,
      "moneda": "COP"
    },
    "stock": 489,
    "descripcion": "Artesanía hecha a mano por comunidades locales. Producto original con excelente calidad.",
    "especificaciones": {
      "color": "gris",
      "talla": null,
      "peso_kg": 3.04
    },
    "imagenes": [
      "https://img.ejemplo.com/img_ozy3h4.jpg",
      "https://img.ejemplo.com/img_pb5gut.jpg",
      "https://img.ejemplo.com/img_dkbtci.jpg"
    ],
    "rating_promedio": 5.0,
    "num_resenas": 1,
    "tags": [
      "premium"
    ],
    "fecha_creacion": "2021-02-22",
    "activo": true
  },
  {
    "_id": "prd_9w457qw66k",
    "nombre": "Portátil 14'' i5 16GB 257",
    "categoria_id": "cat_ig7gpfbsxi",
    "marca": "Asus",
    "precio": {
      "valor": 1670.23,
      "moneda": "COP"
    },
    "stock": 301,
    "descripcion": "Perfecto para regalo o colección. Producto original con excelente calidad.",
    "especificaciones": {
      "color": "gris",
      "talla": "XL",
      "peso_kg": 4.03
    },
    "imagenes": [
      "https://img.ejemplo.com/img_c0dqqd.jpg"
    ],
    "rating_promedio": 5.0,
    "num_resenas": 1,
    "tags": [
      "importado",
      "nuevo"
    ],
    "fecha_creacion": "2021-06-02",
    "activo": true
  },
  {
    "_id": "prd_mg4lgabn2f",
    "nombre": "Portátil 14'' i5 16GB 354",
    "categoria_id": "cat_ig7gpfbsxi",
    "marca": "Asus",
    "precio": {
      "valor": 1153.95,
      "moneda": "COP"
    },
    "stock": 256,
    "descripcion": "Producto original con excelente calidad. Ideal para uso diario y recomendado por compradores.",
    "especificaciones": {
      "color": "gris",
      "talla": "L",
      "peso_kg": 4.52
    },
    "imagenes": [
      "https://img.ejemplo.com/img_gsnwyi.jpg",
      "https://img.ejemplo.com/img_gpu6kp.jpg"
    ],
    "rating_promedio": 3.5,
    "num_resenas": 2,
    "tags": [
      "oferta",
      "popular"
    ],
    "fecha_creacion": "2022-12-27",
    "activo": true
  },
  {
    "_id": "prd_hi8dacq8zf",
    "nombre": "Zapatillas running 824",
    "categoria_id": "cat_a7pf17yp91",
    "marca": "Adidas",
    "precio": {
      "valor": 81.16,
      "moneda": "COP"
    },
    "stock": 388,
    "descripcion": "Envío rápido y empaque seguro. Material resistente y acabado premium.",
    "especificaciones": {
      "color": "rojo",
      "talla": "M",
      "peso_kg": 3.06
    },
    "imagenes": [
      "https://img.ejemplo.com/img_k08vp3.jpg",
      "https://img.ejemplo.com/img_nnrnm2.jpg",
      "https://img.ejemplo.com/img_1zn31n.jpg"
    ],
    "rating_promedio": 0.0,
    "num_resenas": 0,
    "tags": [
      "eco",
      "importado"
    ],
    "fecha_creacion": "2023-09-12",
    "activo": true
  },
  {
    "_id": "prd_496bn6n2p2",
    "nombre": "Mouse inalámbrico 970",
    "categoria_id": "cat_ig7gpfbsxi",
    "marca": "Logitech",
    "precio": {
      "valor": 311.6,
      "moneda": "COP"
    },
    "stock": 500,
    "descripcion": "Producto original con excelente calidad. Material resistente y acabado premium.",
    "especificaciones": {
      "color": "blanco",
      "talla": null,
      "peso_kg": 1.29
    },
    "imagenes": [
      "https://img.ejemplo.com/img_bcf7eo.jpg"
    ],
    "rating_promedio": 5.0,
    "num_resenas": 1,
    "tags": [
      "importado",
      "nuevo",
      "oferta"
    ],
    "fecha_creacion": "2023-06-09",
    "activo": true
  },
  {
    "_id": "prd_9wlwu3f64u",
    "nombre": "Zapatillas running 557",
    "categoria_id": "cat_a7pf17yp91",
    "marca": "Nike",
    "precio": {
      "valor": 1196.64,
      "moneda": "COP"
    },
    "stock": 42,
    "descripcion": "Producto original con excelente calidad. Sabor tradicional colombiano y frescura garantizada.",
    "especificaciones": {
      "color": "azul",
      "talla": "S",
      "peso_kg": 3.26
    },
    "imagenes": [
      "https://img.ejemplo.com/img_6fckgn.jpg"
    ],
    "rating_promedio": 0.0,
    "num_resenas": 0,
    "tags": [
      "eco",
      "popular"
    ],
    "fecha_creacion": "2024-03-29",
    "activo": true
  },
  {
    "_id": "prd_3rwairtx6k",
    "nombre": "Rompecabezas 1000 piezas 668",
    "categoria_id": "cat_hvuwggm7mv",
    "marca": "Hasbro",
    "precio": {
      "valor": 885.26,
      "moneda": "COP"
    },
    "stock": 356,
    "descripcion": "Sabor tradicional colombiano y frescura garantizada. Artesanía hecha a mano por comunidades locales.",
    "especificaciones": {
      "color": "negro",
      "talla": "M",
      "peso_kg": 2.02
    },
    "imagenes": [
      "https://img.ejemplo.com/img_ziyo81.jpg"
    ],
    "rating_promedio": 4.8,
    "num_resenas": 4,
    "tags": [
      "nuevo",
      "popular"
    ],
    "fecha_creacion": "2024-05-03",
    "activo": true
  },
  {
    "_id": "prd_opeleu25zm",
    "nombre": "Zapatillas running 110",
    "categoria_id": "cat_a7pf17yp91",
    "marca": "Adidas",
    "precio": {
      "valor": 251.61,
      "moneda": "COP"
    },
    "stock": 51,
    "descripcion": "Disponible en varias tallas y colores. Perfecto para regalo o colección.",
    "especificaciones": {
      "color": "rojo",
      "talla": null,
      "peso_kg": 0.58
    },
    "imagenes": [
      "https://img.ejemplo.com/img_04e1x0.jpg",
      "https://img.ejemplo.com/img_08a29s.jpg",
      "https://img.ejemplo.com/img_se979d.jpg"
    ],
    "rating_promedio": 5.0,
    "num_resenas": 2,
    "tags": [
      "premium"
    ],
    "fecha_creacion": "2021-05-08",
    "activo": true
  },
  {
    "_id": "prd_57bcjn1nnp",
    "nombre": "Mouse inalámbrico 165",
    "categoria_id": "cat_ig7gpfbsxi",
    "marca": "Microsoft",
    "precio": {
      "valor": 548.38,
      "moneda": "COP"
    },
    "stock": 361,
    "descripcion": "Artesanía hecha a mano por comunidades locales. Perfecto para regalo o colección.",
    "especificaciones": {
      "color": "rojo",
      "talla": "L",
      "peso_kg": 4.08
    },
    "imagenes": [
      "https://img.ejemplo.com/img_i7pwrh.jpg",
      "https://img.ejemplo.com/img_00yfrg.jpg",
      "https://img.ejemplo.com/img_k7z5r0.jpg"
    ],
    "rating_promedio": 4.0,
    "num_resenas": 1,
    "tags": [
      "nuevo"
    ],
    "fecha_creacion": "2022-10-24",
    "activo": true
  },
  {
    "_id": "prd_iymm9cpx49",
    "nombre": "Sartén antiadherente 24cm 247",
    "categoria_id": "cat_wblre8nf3e",
    "marca": "Oster",
    "precio": {
      "valor": 439.41,
      "moneda": "COP"
    },
    "stock": 449,
    "descripcion": "Sabor tradicional colombiano y frescura garantizada. Perfecto para regalo o colección.",
    "especificaciones": {
      "color": "negro",
      "talla": "XS",
      "peso_kg": 1.91
    },
    "imagenes": [
      "https://img.ejemplo.com/img_6utnpr.jpg",
      "https://img.ejemplo.com/img_gjlyuy.jpg"
    ],
    "rating_promedio": 0.0,
    "num_resenas": 0,
    "tags": [
      "nuevo"
    ],
    "fecha_creacion": "2023-06-16",
    "activo": true
  },
  {
    "_id": "prd_emflgy73y2",
    "nombre": "Sartén antiadherente 24cm 370",
    "categoria_id": "cat_wblre8nf3e",
    "marca": "Tramontina",
    "precio": {
      "valor": 1637.17,
      "moneda": "COP"
    },
    "stock": 226,
    "descripcion": "Artesanía hecha a mano por comunidades locales. Producto original con excelente calidad.",
    "especificaciones": {
      "color": "blanco",
      "talla": null,
      "peso_kg": 2.01
    },
    "imagenes": [
      "https://img.ejemplo.com/img_og6avo.jpg",
      "https://img.ejemplo.com/img_l5mc83.jpg"
    ],
    "rating_promedio": 5.0,
    "num_resenas": 4,
    "tags": [
      "importado",
      "popular"
    ],
    "fecha_creacion": "2022-05-08",
    "activo": true
  },
  {
    "_id": "prd_kthspglkwy",
    "nombre": "Zapatillas running 377",
    "categoria_id": "cat_a7pf17yp91",
    "marca": "Puma",
    "precio": {
      "valor": 489.35,
      "moneda": "COP"
    },
    "stock": 178,
    "descripcion": "Sabor tradicional colombiano y frescura garantizada. Artesanía hecha a mano por comunidades locales.",
    "especificaciones": {
      "color": "blanco",
      "talla": null,
      "peso_kg": 1.68
    },
    "imagenes": [
      "https://img.ejemplo.com/img_24x68e.jpg",
      "https://img.ejemplo.com/img_8qr3s1.jpg"
    ],
    "rating_promedio": 3.5,
    "num_resenas": 2,
    "tags": [
      "popular",
      "premium",
      "eco"
    ],
    "fecha_creacion": "2023-09-11",
    "activo": true
  },
  {
    "_id": "prd_04rmv2voqy",
    "nombre": "Portátil 14'' i5 16GB 481",
    "categoria_id": "cat_ig7gpfbsxi",
    "marca": "Dell",
    "precio": {
      "valor": 673.68,
      "moneda": "COP"
    },
    "stock": 196,
    "descripcion": "Envío rápido y empaque seguro. Disponible en varias tallas y colores.",
    "especificaciones": {
      "color": "gris",
      "talla": "XL",
      "peso_kg": 2.98
    },
    "imagenes": [
      "https://img.ejemplo.com/img_oyzur6.jpg"
    ],
    "rating_promedio": 4.0,
    "num_resenas": 1,
    "tags": [
      "importado"
    ],
    "fecha_creacion": "2022-10-24",
    "activo": true
  },
  {
    "_id": "prd_yo84yo3nv6",
    "nombre": "Smartwatch deportivo 962",
    "categoria_id": "cat_fywrh23ssi",
    "marca": "Huawei",
    "precio": {
      "valor": 1147.64,
      "moneda": "COP"
    },
    "stock": 281,
    "descripcion": "Producto original con excelente calidad. Artesanía hecha a mano por comunidades locales.",
    "especificaciones": {
      "color": "azul",
      "talla": null,
      "peso_kg": 2.65
    },
    "imagenes": [
      "https://img.ejemplo.com/img_ekr03f.jpg",
      "https://img.ejemplo.com/img_hbjprn.jpg",
      "https://img.ejemplo.com/img_udryq9.jpg"
    ],
    "rating_promedio": 5.0,
    "num_resenas": 1,
    "tags": [
      "eco"
    ],
    "fecha_creacion": "2023-08-20",
    "activo": true
  },
  {
    "_id": "prd_yxq7idnhhj",
    "nombre": "Portátil 14'' i5 16GB 220",
    "categoria_id": "cat_ig7gpfbsxi",
    "marca": "Asus",
    "precio": {
      "valor": 318.23,
      "moneda": "COP"
    },
    "stock": 445,
    "descripcion": "Sabor tradicional colombiano y frescura garantizada. Envío rápido y empaque seguro.",
    "especificaciones": {
      "color": "blanco",
      "talla": "L",
      "peso_kg": 4.79
    },
    "imagenes": [
      "https://img.ejemplo.com/img_xwrgci.jpg"
    ],
    "rating_promedio": 5.0,
    "num_resenas": 1,
    "tags": [
      "eco"
    ],
    "fecha_creacion": "2023-01-22",
    "activo": true
  },
  {
    "_id": "prd_yf0k8s16ll",
    "nombre": "Zapatillas running 532",
    "categoria_id": "cat_a7pf17yp91",
    "marca": "Adidas",
    "precio": {
      "valor": 1502.27,
      "moneda": "COP"
    },
    "stock": 378,
    "descripcion": "Envío rápido y empaque seguro. Disponible en varias tallas y colores.",
    "especificaciones": {
      "color": "negro",
      "talla": "S",
      "peso_kg": 0.29
    },
    "imagenes": [
      "https://img.ejemplo.com/img_4b31xx.jpg",
      "https://img.ejemplo.com/img_jirawe.jpg"
    ],
    "rating_promedio": 4.5,
    "num_resenas": 2,
    "tags": [
      "oferta",
      "popular"
    ],
    "fecha_creacion": "2021-11-24",
    "activo": true
  },
  {
    "_id": "prd_v6gmh2soot",
    "nombre": "Portátil 14'' i5 16GB 353",
    "categoria_id": "cat_ig7gpfbsxi",
    "marca": "Lenovo",
    "precio": {
      "valor": 1635.1,
      "moneda": "COP"
    },
    "stock": 429,
    "descripcion": "Envío rápido y empaque seguro. Material resistente y acabado premium.",
    "especificaciones": {
      "color": "azul",
      "talla": "XL",
      "peso_kg": 0.82
    },
    "imagenes": [
      "https://img.ejemplo.com/img_vcgek3.jpg",
      "https://img.ejemplo.com/img_voxado.jpg"
    ],
    "rating_promedio": 0.0,
    "num_resenas": 0,
    "tags": [
      "eco",
      "popular",
      "nuevo"
    ],
    "fecha_creacion": "2022-07-29",
    "activo": false
  },
  {
    "_id": "prd_5tgrh2j9h0",
    "nombre": "Portátil 14'' i5 16GB 171",
    "categoria_id": "cat_ig7gpfbsxi",
    "marca": "Lenovo",
    "precio": {
      "valor": 1674.0,
      "moneda": "COP"
    },
    "stock": 114,
    "descripcion": "Sabor tradicional colombiano y frescura garantizada. Material resistente y acabado premium.",
    "especificaciones": {
      "color": "rojo",
      "talla": "XS",
      "peso_kg": 2.16
    },
    "imagenes": [
      "https://img.ejemplo.com/img_wi7duv.jpg",
      "https://img.ejemplo.com/img_1lawyq.jpg",
      "https://img.ejemplo.com/img_kki5qc.jpg"
    ],
    "rating_promedio": 4.0,
    "num_resenas": 3,
    "tags": [
      "importado",
      "eco",
      "premium"
    ],
    "fecha_creacion": "2023-04-08",
    "activo": true
  },
  {
    "_id": "prd_ynko3yagf1",
    "nombre": "Portátil 14'' i5 16GB 331",
    "categoria_id": "cat_ig7gpfbsxi",
    "marca": "Dell",
    "precio": {
      "valor": 292.15,
      "moneda": "COP"
    },
    "stock": 110,
    "descripcion": "Perfecto para regalo o colección. Envío rápido y empaque seguro.",
    "especificaciones": {
      "color": "blanco",
      "talla": "XS",
      "peso_kg": 4.88
    },
    "imagenes": [
      "https://img.ejemplo.com/img_nfvid3.jpg"
    ],
    "rating_promedio": 4.0,
    "num_resenas": 1,
    "tags": [
      "nuevo"
    ],
    "fecha_creacion": "2021-01-25",
    "activo": true
  },
  {
    "_id": "prd_i6y6nibzri",
    "nombre": "Mouse inalámbrico 684",
    "categoria_id": "cat_ig7gpfbsxi",
    "marca": "Microsoft",
    "precio": {
      "valor": 95.73,
      "moneda": "COP"
    },
    "stock": 264,
    "descripcion": "Producto original con excelente calidad. Artesanía hecha a mano por comunidades locales.",
    "especificaciones": {
      "color": "gris",
      "talla": null,
      "peso_kg": 2.03
    },
    "imagenes": [
      "https://img.ejemplo.com/img_j9hg2v.jpg"
    ],
    "rating_promedio": 5.0,
    "num_resenas": 1,
    "tags": [
      "popular"
    ],
    "fecha_creacion": "2023-03-10",
    "activo": true
  },
  {
    "_id": "prd_xfrcvknhbs",
    "nombre": "Portátil 14'' i5 16GB 533",
    "categoria_id": "cat_ig7gpfbsxi",
    "marca": "HP",
    "precio": {
      "valor": 1166.63,
      "moneda": "COP"
    },
    "stock": 343,
    "descripcion": "Artesanía hecha a mano por comunidades locales. Sabor tradicional colombiano y frescura garantizada.",
    "especificaciones": {
      "color": "gris",
      "talla": "S",
      "peso_kg": 2.96
    },
    "imagenes": [
      "https://img.ejemplo.com/img_97xk4v.jpg",
      "https://img.ejemplo.com/img_p6lbeo.jpg"
    ],
    "rating_promedio": 0.0,
    "num_resenas": 0,
    "tags": [
      "oferta",
      "importado"
    ],
    "fecha_creacion": "2025-11-16",
    "activo": true
  },
  {
    "_id": "prd_6i5epjgo8i",
    "nombre": "Portátil 14'' i5 16GB 615",
    "categoria_id": "cat_ig7gpfbsxi",
    "marca": "HP",
    "precio": {
      "valor": 1749.63,
      "moneda": "COP"
    },
    "stock": 24,
    "descripcion": "Sabor tradicional colombiano y frescura garantizada. Perfecto para regalo o colección.",
    "especificaciones": {
      "color": "negro",
      "talla": "S",
      "peso_kg": 2.28
    },
    "imagenes": [
      "https://img.ejemplo.com/img_4fql6n.jpg",
      "https://img.ejemplo.com/img_ekqx15.jpg"
    ],
    "rating_promedio": 0.0,
    "num_resenas": 0,
    "tags": [
      "importado"
    ],
    "fecha_creacion": "2023-05-21",
    "activo": true
  },
  {
    "_id": "prd_pl89g2yy3a",
    "nombre": "Juguete para perro resistente 985",
    "categoria_id": "cat_ck4xbio5xf",
    "marca": "Purina",
    "precio": {
      "valor": 1332.76,
      "moneda": "COP"
    },
    "stock": 476,
    "descripcion": "Perfecto para regalo o colección. Artesanía hecha a mano por comunidades locales.",
    "especificaciones": {
      "color": "negro",
      "talla": "L",
      "peso_kg": 4.1
    },
    "imagenes": [
      "https://img.ejemplo.com/img_ar2ugv.jpg"
    ],
    "rating_promedio": 4.5,
    "num_resenas": 2,
    "tags": [
      "importado",
      "premium",
      "eco"
    ],
    "fecha_creacion": "2025-08-04",
    "activo": true
  },
  {
    "_id": "prd_7vni7s9e6b",
    "nombre": "Portátil 14'' i5 16GB 267",
    "categoria_id": "cat_ig7gpfbsxi",
    "marca": "Asus",
    "precio": {
      "valor": 1788.52,
      "moneda": "COP"
    },
    "stock": 300,
    "descripcion": "Perfecto para regalo o colección. Sabor tradicional colombiano y frescura garantizada.",
    "especificaciones": {
      "color": "blanco",
      "talla": null,
      "peso_kg": 3.21
    },
    "imagenes": [
      "https://img.ejemplo.com/img_v83zyx.jpg",
      "https://img.ejemplo.com/img_6ys3pq.jpg"
    ],
    "rating_promedio": 0.0,
    "num_resenas": 0,
    "tags": [
      "importado",
      "oferta"
    ],
    "fecha_creacion": "2022-07-12",
    "activo": true
  },
  {
    "_id": "prd_exn7ihm00h",
    "nombre": "Rompecabezas 1000 piezas 847",
    "categoria_id": "cat_hvuwggm7mv",
    "marca": "Ravensburger",
    "precio": {
      "valor": 435.73,
      "moneda": "COP"
    },
    "stock": 147,
    "descripcion": "Ideal para uso diario y recomendado por compradores. Sabor tradicional colombiano y frescura garantizada.",
    "especificaciones": {
      "color": "verde",
      "talla": "L",
      "peso_kg": 2.54
    },
    "imagenes": [
      "https://img.ejemplo.com/img_xbp7u4.jpg",
      "https://img.ejemplo.com/img_86oba8.jpg"
    ],
    "rating_promedio": 5.0,
    "num_resenas": 1,
    "tags": [
      "oferta",
      "importado"
    ],
    "fecha_creacion": "2024-02-13",
    "activo": true
  },
  {
    "_id": "prd_uz2azcnzmv",
    "nombre": "Crema hidratante corporal 229",
    "categoria_id": "cat_9cuunmftk8",
    "marca": "L'Oréal",
    "precio": {
      "valor": 1180.86,
      "moneda": "COP"
    },
    "stock": 299,
    "descripcion": "Material resistente y acabado premium. Artesanía hecha a mano por comunidades locales.",
    "especificaciones": {
      "color": "negro",
      "talla": "L",
      "peso_kg": 4.21
    },
    "imagenes": [
      "https://img.ejemplo.com/img_pueb4p.jpg",
      "https://img.ejemplo.com/img_wvogaq.jpg",
      "https://img.ejemplo.com/img_dgfurv.jpg"
    ],
    "rating_promedio": 5.0,
    "num_resenas": 3,
    "tags": [
      "importado",
      "premium"
    ],
    "fecha_creacion": "2023-07-31",
    "activo": true
  },
  {
    "_id": "prd_o6o0ges3ub",
    "nombre": "Sartén antiadherente 24cm 279",
    "categoria_id": "cat_wblre8nf3e",
    "marca": "Oster",
    "precio": {
      "valor": 800.7,
      "moneda": "COP"
    },
    "stock": 396,
    "descripcion": "Producto original con excelente calidad. Material resistente y acabado premium.",
    "especificaciones": {
      "color": "gris",
      "talla": "M",
      "peso_kg": 4.93
    },
    "imagenes": [
      "https://img.ejemplo.com/img_5g3xwy.jpg",
      "https://img.ejemplo.com/img_kxuakc.jpg",
      "https://img.ejemplo.com/img_zdr4yc.jpg"
    ],
    "rating_promedio": 5.0,
    "num_resenas": 1,
    "tags": [
      "oferta",
      "importado",
      "nuevo"
    ],
    "fecha_creacion": "2025-11-30",
    "activo": true
  },
  {
    "_id": "prd_ui5xjcucvo",
    "nombre": "Mouse inalámbrico 464",
    "categoria_id": "cat_ig7gpfbsxi",
    "marca": "Logitech",
    "precio": {
      "valor": 32.52,
      "moneda": "COP"
    },
    "stock": 127,
    "descripcion": "Material resistente y acabado premium. Ideal para uso diario y recomendado por compradores.",
    "especificaciones": {
      "color": "negro",
      "talla": "S",
      "peso_kg": 0.75
    },
    "imagenes": [
      "https://img.ejemplo.com/img_u18lvo.jpg",
      "https://img.ejemplo.com/img_fn60pt.jpg"
    ],
    "rating_promedio": 0.0,
    "num_resenas": 0,
    "tags": [
      "oferta",
      "eco"
    ],
    "fecha_creacion": "2021-10-17",
    "activo": true
  },
  {
    "_id": "prd_chnkz0xpzu",
    "nombre": "Juguete para perro resistente 465",
    "categoria_id": "cat_ck4xbio5xf",
    "marca": "Kong",
    "precio": {
      "valor": 774.43,
      "moneda": "COP"
    },
    "stock": 170,
    "descripcion": "Artesanía hecha a mano por comunidades locales. Envío rápido y empaque seguro.",
    "especificaciones": {
      "color": "gris",
      "talla": "S",
      "peso_kg": 0.29
    },
    "imagenes": [
      "https://img.ejemplo.com/img_hwskeq.jpg",
      "https://img.ejemplo.com/img_u9izqi.jpg",
      "https://img.ejemplo.com/img_icbj7u.jpg"
    ],
    "rating_promedio": 5.0,
    "num_resenas": 1,
    "tags": [
      "premium"
    ],
    "fecha_creacion": "2022-05-30",
    "activo": true
  },
  {
    "_id": "prd_b5bktpeahh",
    "nombre": "Zapatillas running 539",
    "categoria_id": "cat_a7pf17yp91",
    "marca": "Nike",
    "precio": {
      "valor": 1735.07,
      "moneda": "COP"
    },
    "stock": 59,
    "descripcion": "Envío rápido y empaque seguro. Disponible en varias tallas y colores.",
    "especificaciones": {
      "color": "rojo",
      "talla": "XL",
      "peso_kg": 3.53
    },
    "imagenes": [
      "https://img.ejemplo.com/img_1zc4wd.jpg"
    ],
    "rating_promedio": 0.0,
    "num_resenas": 0,
    "tags": [
      "importado",
      "nuevo"
    ],
    "fecha_creacion": "2023-04-15",
    "activo": true
  },
  {
    "_id": "prd_dxcewl7mga",
    "nombre": "Juguete para perro resistente 697",
    "categoria_id": "cat_ck4xbio5xf",
    "marca": "Kong",
    "precio": {
      "valor": 361.99,
      "moneda": "COP"
    },
    "stock": 291,
    "descripcion": "Artesanía hecha a mano por comunidades locales. Ideal para uso diario y recomendado por compradores.",
    "especificaciones": {
      "color": "negro",
      "talla": "XS",
      "peso_kg": 0.34
    },
    "imagenes": [
      "https://img.ejemplo.com/img_t3ozd2.jpg"
    ],
    "rating_promedio": 5.0,
    "num_resenas": 1,
    "tags": [
      "premium",
      "nuevo"
    ],
    "fecha_creacion": "2023-12-17",
    "activo": true
  },
  {
    "_id": "prd_fizq4by2s9",
    "nombre": "Juguete para perro resistente 395",
    "categoria_id": "cat_ck4xbio5xf",
    "marca": "Purina",
    "precio": {
      "valor": 742.34,
      "moneda": "COP"
    },
    "stock": 217,
    "descripcion": "Material resistente y acabado premium. Artesanía hecha a mano por comunidades locales.",
    "especificaciones": {
      "color": "rojo",
      "talla": "XS",
      "peso_kg": 2.77
    },
    "imagenes": [
      "https://img.ejemplo.com/img_amx1i8.jpg"
    ],
    "rating_promedio": 0.0,
    "num_resenas": 0,
    "tags": [
      "oferta",
      "popular",
      "eco"
    ],
    "fecha_creacion": "2025-04-16",
    "activo": true
  },
  {
    "_id": "prd_muqyjvourn",
    "nombre": "Smartwatch deportivo 720",
    "categoria_id": "cat_fywrh23ssi",
    "marca": "Samsung",
    "precio": {
      "valor": 1344.07,
      "moneda": "COP"
    },
    "stock": 307,
    "descripcion": "Ideal para uso diario y recomendado por compradores. Perfecto para regalo o colección.",
    "especificaciones": {
      "color": "negro",
      "talla": "M",
      "peso_kg": 4.68
    },
    "imagenes": [
      "https://img.ejemplo.com/img_9qq1vs.jpg",
      "https://img.ejemplo.com/img_h4fbbc.jpg",
      "https://img.ejemplo.com/img_hlybwa.jpg"
    ],
    "rating_promedio": 0.0,
    "num_resenas": 0,
    "tags": [
      "importado",
      "premium",
      "oferta"
    ],
    "fecha_creacion": "2023-04-28",
    "activo": true
  },
  {
    "_id": "prd_qqqd5qw6lb",
    "nombre": "Sartén antiadherente 24cm 965",
    "categoria_id": "cat_wblre8nf3e",
    "marca": "Tramontina",
    "precio": {
      "valor": 1129.95,
      "moneda": "COP"
    },
    "stock": 368,
    "descripcion": "Artesanía hecha a mano por comunidades locales. Ideal para uso diario y recomendado por compradores.",
    "especificaciones": {
      "color": "blanco",
      "talla": "XS",
      "peso_kg": 4.28
    },
    "imagenes": [
      "https://img.ejemplo.com/img_lr391v.jpg",
      "https://img.ejemplo.com/img_3378hn.jpg"
    ],
    "rating_promedio": 5.0,
    "num_resenas": 2,
    "tags": [
      "premium"
    ],
    "fecha_creacion": "2023-02-19",
    "activo": true
  },
  {
    "_id": "prd_gnvjxo5x0b",
    "nombre": "Sartén antiadherente 24cm 334",
    "categoria_id": "cat_wblre8nf3e",
    "marca": "Tramontina",
    "precio": {
      "valor": 1402.86,
      "moneda": "COP"
    },
    "stock": 112,
    "descripcion": "Disponible en varias tallas y colores. Material resistente y acabado premium.",
    "especificaciones": {
      "color": "rojo",
      "talla": "XL",
      "peso_kg": 2.09
    },
    "imagenes": [
      "https://img.ejemplo.com/img_d5upx4.jpg",
      "https://img.ejemplo.com/img_83ivqz.jpg",
      "https://img.ejemplo.com/img_lt5bi0.jpg"
    ],
    "rating_promedio": 0.0,
    "num_resenas": 0,
    "tags": [
      "oferta",
      "eco",
      "premium"
    ],
    "fecha_creacion": "2025-02-25",
    "activo": true
  },
  {
    "_id": "prd_b4f3lb0fy7",
    "nombre": "Zapatillas running 175",
    "categoria_id": "cat_a7pf17yp91",
    "marca": "Nike",
    "precio": {
      "valor": 636.45,
      "moneda": "COP"
    },
    "stock": 317,
    "descripcion": "Disponible en varias tallas y colores. Sabor tradicional colombiano y frescura garantizada.",
    "especificaciones": {
      "color": "azul",
      "talla": "XL",
      "peso_kg": 3.98
    },
    "imagenes": [
      "https://img.ejemplo.com/img_xsp2zj.jpg",
      "https://img.ejemplo.com/img_cxi0r8.jpg"
    ],
    "rating_promedio": 5.0,
    "num_resenas": 1,
    "tags": [
      "popular",
      "eco"
    ],
    "fecha_creacion": "2021-06-30",
    "activo": true
  },
  {
    "_id": "prd_9nx1h4v4af",
    "nombre": "Mouse inalámbrico 671",
    "categoria_id": "cat_ig7gpfbsxi",
    "marca": "Logitech",
    "precio": {
      "valor": 655.59,
      "moneda": "COP"
    },
    "stock": 29,
    "descripcion": "Envío rápido y empaque seguro. Sabor tradicional colombiano y frescura garantizada.",
    "especificaciones": {
      "color": "verde",
      "talla": "L",
      "peso_kg": 4.91
    },
    "imagenes": [
      "https://img.ejemplo.com/img_kdfeiy.jpg",
      "https://img.ejemplo.com/img_61k3qj.jpg"
    ],
    "rating_promedio": 0.0,
    "num_resenas": 0,
    "tags": [
      "premium",
      "popular",
      "nuevo"
    ],
    "fecha_creacion": "2021-02-06",
    "activo": false
  },
  {
    "_id": "prd_e4l75k850k",
    "nombre": "Juguete para perro resistente 640",
    "categoria_id": "cat_ck4xbio5xf",
    "marca": "Kong",
    "precio": {
      "valor": 696.6,
      "moneda": "COP"
    },
    "stock": 166,
    "descripcion": "Ideal para uso diario y recomendado por compradores. Material resistente y acabado premium.",
    "especificaciones": {
      "color": "gris",
      "talla": "L",
      "peso_kg": 1.55
    },
    "imagenes": [
      "https://img.ejemplo.com/img_m9lrag.jpg"
    ],
    "rating_promedio": 0.0,
    "num_resenas": 0,
    "tags": [
      "popular"
    ],
    "fecha_creacion": "2023-07-11",
    "activo": true
  },
  {
    "_id": "prd_wz8gu3jt0s",
    "nombre": "Rompecabezas 1000 piezas 725",
    "categoria_id": "cat_hvuwggm7mv",
    "marca": "Mattel",
    "precio": {
      "valor": 201.96,
      "moneda": "COP"
    },
    "stock": 109,
    "descripcion": "Perfecto para regalo o colección. Artesanía hecha a mano por comunidades locales.",
    "especificaciones": {
      "color": "blanco",
      "talla": "XL",
      "peso_kg": 3.69
    },
    "imagenes": [
      "https://img.ejemplo.com/img_vuyxzw.jpg",
      "https://img.ejemplo.com/img_olb0dc.jpg"
    ],
    "rating_promedio": 0.0,
    "num_resenas": 0,
    "tags": [
      "premium"
    ],
    "fecha_creacion": "2025-11-19",
    "activo": true
  },
  {
    "_id": "prd_yggj9dpzd2",
    "nombre": "Crema hidratante corporal 599",
    "categoria_id": "cat_9cuunmftk8",
    "marca": "L'Oréal",
    "precio": {
      "valor": 1508.3,
      "moneda": "COP"
    },
    "stock": 442,
    "descripcion": "Artesanía hecha a mano por comunidades locales. Perfecto para regalo o colección.",
    "especificaciones": {
      "color": "rojo",
      "talla": "M",
      "peso_kg": 0.19
    },
    "imagenes": [
      "https://img.ejemplo.com/img_xndz3o.jpg"
    ],
    "rating_promedio": 0.0,
    "num_resenas": 0,
    "tags": [
      "eco"
    ],
    "fecha_creacion": "2021-08-23",
    "activo": true
  },
  {
    "_id": "prd_az7thz5uu1",
    "nombre": "Crema hidratante corporal 975",
    "categoria_id": "cat_9cuunmftk8",
    "marca": "L'Oréal",
    "precio": {
      "valor": 1052.34,
      "moneda": "COP"
    },
    "stock": 71,
    "descripcion": "Perfecto para regalo o colección. Producto original con excelente calidad.",
    "especificaciones": {
      "color": "azul",
      "talla": null,
      "peso_kg": 0.55
    },
    "imagenes": [
      "https://img.ejemplo.com/img_q5ay51.jpg",
      "https://img.ejemplo.com/img_htt53j.jpg"
    ],
    "rating_promedio": 4.7,
    "num_resenas": 3,
    "tags": [
      "importado",
      "nuevo",
      "premium"
    ],
    "fecha_creacion": "2021-09-20",
    "activo": true
  },
  {
    "_id": "prd_34dqmd5nvc",
    "nombre": "Mouse inalámbrico 307",
    "categoria_id": "cat_ig7gpfbsxi",
    "marca": "Microsoft",
    "precio": {
      "valor": 137.9,
      "moneda": "COP"
    },
    "stock": 433,
    "descripcion": "Envío rápido y empaque seguro. Ideal para uso diario y recomendado por compradores.",
    "especificaciones": {
      "color": "rojo",
      "talla": "L",
      "peso_kg": 3.65
    },
    "imagenes": [
      "https://img.ejemplo.com/img_21qv48.jpg",
      "https://img.ejemplo.com/img_gdb57v.jpg"
    ],
    "rating_promedio": 0.0,
    "num_resenas": 0,
    "tags": [
      "oferta",
      "importado",
      "nuevo"
    ],
    "fecha_creacion": "2025-10-09",
    "activo": true
  },
  {
    "_id": "prd_09tfor415b",
    "nombre": "Portátil 14'' i5 16GB 669",
    "categoria_id": "cat_ig7gpfbsxi",
    "marca": "Asus",
    "precio": {
      "valor": 64.14,
      "moneda": "COP"
    },
    "stock": 8,
    "descripcion": "Material resistente y acabado premium. Sabor tradicional colombiano y frescura garantizada.",
    "especificaciones": {
      "color": "gris",
      "talla": "L",
      "peso_kg": 4.78
    },
    "imagenes": [
      "https://img.ejemplo.com/img_pfylpp.jpg",
      "https://img.ejemplo.com/img_ybviej.jpg",
      "https://img.ejemplo.com/img_5k982r.jpg"
    ],
    "rating_promedio": 0.0,
    "num_resenas": 0,
    "tags": [
      "oferta"
    ],
    "fecha_creacion": "2021-11-26",
    "activo": true
  },
  {
    "_id": "prd_kyirye51z5",
    "nombre": "Crema hidratante corporal 450",
    "categoria_id": "cat_9cuunmftk8",
    "marca": "Nivea",
    "precio": {
      "valor": 1673.67,
      "moneda": "COP"
    },
    "stock": 53,
    "descripcion": "Material resistente y acabado premium. Ideal para uso diario y recomendado por compradores.",
    "especificaciones": {
      "color": "rojo",
      "talla": "XL",
      "peso_kg": 1.29
    },
    "imagenes": [
      "https://img.ejemplo.com/img_nmcjud.jpg",
      "https://img.ejemplo.com/img_p6qih4.jpg",
      "https://img.ejemplo.com/img_2lsxgu.jpg"
    ],
    "rating_promedio": 5.0,
    "num_resenas": 1,
    "tags": [
      "nuevo"
    ],
    "fecha_creacion": "2022-12-01",
    "activo": true
  },
  {
    "_id": "prd_ts4uw1x7er",
    "nombre": "Mouse inalámbrico 137",
    "categoria_id": "cat_ig7gpfbsxi",
    "marca": "Microsoft",
    "precio": {
      "valor": 137.33,
      "moneda": "COP"
    },
    "stock": 348,
    "descripcion": "Material resistente y acabado premium. Ideal para uso diario y recomendado por compradores.",
    "especificaciones": {
      "color": "blanco",
      "talla": "XL",
      "peso_kg": 0.85
    },
    "imagenes": [
      "https://img.ejemplo.com/img_8hzkf4.jpg",
      "https://img.ejemplo.com/img_4l0bzs.jpg"
    ],
    "rating_promedio": 0.0,
    "num_resenas": 0,
    "tags": [
      "eco",
      "nuevo"
    ],
    "fecha_creacion": "2024-10-03",
    "activo": true
  },
  {
    "_id": "prd_5v41b587gb",
    "nombre": "Smartwatch deportivo 399",
    "categoria_id": "cat_fywrh23ssi",
    "marca": "Samsung",
    "precio": {
      "valor": 1375.13,
      "moneda": "COP"
    },
    "stock": 416,
    "descripcion": "Artesanía hecha a mano por comunidades locales. Perfecto para regalo o colección.",
    "especificaciones": {
      "color": "blanco",
      "talla": "S",
      "peso_kg": 4.61
    },
    "imagenes": [
      "https://img.ejemplo.com/img_v17kim.jpg",
      "https://img.ejemplo.com/img_4g075z.jpg",
      "https://img.ejemplo.com/img_zweyv8.jpg"
    ],
    "rating_promedio": 0.0,
    "num_resenas": 0,
    "tags": [
      "eco"
    ],
    "fecha_creacion": "2023-01-14",
    "activo": false
  },
  {
    "_id": "prd_har6qdyals",
    "nombre": "Zapatillas running 827",
    "categoria_id": "cat_a7pf17yp91",
    "marca": "Puma",
    "precio": {
      "valor": 1580.53,
      "moneda": "COP"
    },
    "stock": 143,
    "descripcion": "Ideal para uso diario y recomendado por compradores. Artesanía hecha a mano por comunidades locales.",
    "especificaciones": {
      "color": "blanco",
      "talla": "XS",
      "peso_kg": 3.94
    },
    "imagenes": [
      "https://img.ejemplo.com/img_nfyurx.jpg",
      "https://img.ejemplo.com/img_hlh80f.jpg"
    ],
    "rating_promedio": 0.0,
    "num_resenas": 0,
    "tags": [
      "popular"
    ],
    "fecha_creacion": "2021-12-30",
    "activo": true
  },
  {
    "_id": "prd_wa8kclcl3d",
    "nombre": "Juguete para perro resistente 695",
    "categoria_id": "cat_ck4xbio5xf",
    "marca": "Purina",
    "precio": {
      "valor": 1337.41,
      "moneda": "COP"
    },
    "stock": 91,
    "descripcion": "Producto original con excelente calidad. Sabor tradicional colombiano y frescura garantizada.",
    "especificaciones": {
      "color": "azul",
      "talla": "S",
      "peso_kg": 4.41
    },
    "imagenes": [
      "https://img.ejemplo.com/img_urvfgh.jpg",
      "https://img.ejemplo.com/img_xuu5gv.jpg",
      "https://img.ejemplo.com/img_1obmn9.jpg"
    ],
    "rating_promedio": 5.0,
    "num_resenas": 1,
    "tags": [
      "premium",
      "importado"
    ],
    "fecha_creacion": "2024-04-14",
    "activo": true
  },
  {
    "_id": "prd_i3le0qugl7",
    "nombre": "Sartén antiadherente 24cm 364",
    "categoria_id": "cat_wblre8nf3e",
    "marca": "Tramontina",
    "precio": {
      "valor": 736.9,
      "moneda": "COP"
    },
    "stock": 434,
    "descripcion": "Perfecto para regalo o colección. Sabor tradicional colombiano y frescura garantizada.",
    "especificaciones": {
      "color": "gris",
      "talla": null,
      "peso_kg": 3.04
    },
    "imagenes": [
      "https://img.ejemplo.com/img_mlzeu5.jpg",
      "https://img.ejemplo.com/img_nkpksx.jpg"
    ],
    "rating_promedio": 0.0,
    "num_resenas": 0,
    "tags": [
      "premium",
      "importado"
    ],
    "fecha_creacion": "2023-07-28",
    "activo": true
  },
  {
    "_id": "prd_j18zdja4v9",
    "nombre": "Mouse inalámbrico 359",
    "categoria_id": "cat_ig7gpfbsxi",
    "marca": "Logitech",
    "precio": {
      "valor": 1072.89,
      "moneda": "COP"
    },
    "stock": 29,
    "descripcion": "Artesanía hecha a mano por comunidades locales. Sabor tradicional colombiano y frescura garantizada.",
    "especificaciones": {
      "color": "azul",
      "talla": "XL",
      "peso_kg": 0.34
    },
    "imagenes": [
      "https://img.ejemplo.com/img_szauop.jpg"
    ],
    "rating_promedio": 0.0,
    "num_resenas": 0,
    "tags": [
      "eco",
      "premium",
      "oferta"
    ],
    "fecha_creacion": "2025-06-06",
    "activo": true
  },
  {
    "_id": "prd_j5xkhl3i61",
    "nombre": "Zapatillas running 689",
    "categoria_id": "cat_a7pf17yp91",
    "marca": "Puma",
    "precio": {
      "valor": 457.8,
      "moneda": "COP"
    },
    "stock": 143,
    "descripcion": "Sabor tradicional colombiano y frescura garantizada. Disponible en varias tallas y colores.",
    "especificaciones": {
      "color": "negro",
      "talla": "M",
      "peso_kg": 0.67
    },
    "imagenes": [
      "https://img.ejemplo.com/img_3t6ww6.jpg",
      "https://img.ejemplo.com/img_zk8d0l.jpg"
    ],
    "rating_promedio": 5.0,
    "num_resenas": 2,
    "tags": [
      "eco",
      "oferta",
      "nuevo"
    ],
    "fecha_creacion": "2021-06-28",
    "activo": true
  },
  {
    "_id": "prd_9hb6shfz0t",
    "nombre": "Juguete para perro resistente 655",
    "categoria_id": "cat_ck4xbio5xf",
    "marca": "Purina",
    "precio": {
      "valor": 1059.54,
      "moneda": "COP"
    },
    "stock": 373,
    "descripcion": "Producto original con excelente calidad. Artesanía hecha a mano por comunidades locales.",
    "especificaciones": {
      "color": "verde",
      "talla": "M",
      "peso_kg": 2.39
    },
    "imagenes": [
      "https://img.ejemplo.com/img_9kmbyh.jpg"
    ],
    "rating_promedio": 5.0,
    "num_resenas": 1,
    "tags": [
      "nuevo",
      "oferta"
    ],
    "fecha_creacion": "2021-03-23",
    "activo": true
  },
  {
    "_id": "prd_jiv918yyx8",
    "nombre": "Juguete para perro resistente 727",
    "categoria_id": "cat_ck4xbio5xf",
    "marca": "Genérica",
    "precio": {
      "valor": 975.61,
      "moneda": "COP"
    },
    "stock": 268,
    "descripcion": "Sabor tradicional colombiano y frescura garantizada. Ideal para uso diario y recomendado por compradores.",
    "especificaciones": {
      "color": "azul",
      "talla": "XL",
      "peso_kg": 2.68
    },
    "imagenes": [
      "https://img.ejemplo.com/img_l8tvzx.jpg",
      "https://img.ejemplo.com/img_8p4wym.jpg",
      "https://img.ejemplo.com/img_ft23xg.jpg"
    ],
    "rating_promedio": 5.0,
    "num_resenas": 1,
    "tags": [
      "popular"
    ],
    "fecha_creacion": "2025-02-16",
    "activo": true
  },
  {
    "_id": "prd_c6allwojc3",
    "nombre": "Rompecabezas 1000 piezas 958",
    "categoria_id": "cat_hvuwggm7mv",
    "marca": "Mattel",
    "precio": {
      "valor": 440.38,
      "moneda": "COP"
    },
    "stock": 246,
    "descripcion": "Producto original con excelente calidad. Disponible en varias tallas y colores.",
    "especificaciones": {
      "color": "verde",
      "talla": "M",
      "peso_kg": 2.63
    },
    "imagenes": [
      "https://img.ejemplo.com/img_of4iml.jpg",
      "https://img.ejemplo.com/img_qz09cd.jpg",
      "https://img.ejemplo.com/img_casixv.jpg"
    ],
    "rating_promedio": 5.0,
    "num_resenas": 2,
    "tags": [
      "premium",
      "nuevo"
    ],
    "fecha_creacion": "2023-01-30",
    "activo": true
  },
  {
    "_id": "prd_0jmtnfg0di",
    "nombre": "Juguete para perro resistente 585",
    "categoria_id": "cat_ck4xbio5xf",
    "marca": "Genérica",
    "precio": {
      "valor": 1746.62,
      "moneda": "COP"
    },
    "stock": 124,
    "descripcion": "Perfecto para regalo o colección. Sabor tradicional colombiano y frescura garantizada.",
    "especificaciones": {
      "color": "gris",
      "talla": "S",
      "peso_kg": 1.6
    },
    "imagenes": [
      "https://img.ejemplo.com/img_872kii.jpg",
      "https://img.ejemplo.com/img_jyolfj.jpg",
      "https://img.ejemplo.com/img_i28ygx.jpg"
    ],
    "rating_promedio": 5.0,
    "num_resenas": 1,
    "tags": [
      "oferta",
      "importado"
    ],
    "fecha_creacion": "2025-11-13",
    "activo": true
  },
  {
    "_id": "prd_zmdchhap43",
    "nombre": "Zapatillas running 574",
    "categoria_id": "cat_a7pf17yp91",
    "marca": "Nike",
    "precio": {
      "valor": 1668.66,
      "moneda": "COP"
    },
    "stock": 81,
    "descripcion": "Perfecto para regalo o colección. Artesanía hecha a mano por comunidades locales.",
    "especificaciones": {
      "color": "verde",
      "talla": "M",
      "peso_kg": 2.3
    },
    "imagenes": [
      "https://img.ejemplo.com/img_04chfi.jpg",
      "https://img.ejemplo.com/img_4eqa47.jpg",
      "https://img.ejemplo.com/img_ke74v7.jpg"
    ],
    "rating_promedio": 0.0,
    "num_resenas": 0,
    "tags": [
      "eco",
      "nuevo",
      "popular"
    ],
    "fecha_creacion": "2024-03-21",
    "activo": true
  },
  {
    "_id": "prd_267t80iq10",
    "nombre": "Smartwatch deportivo 135",
    "categoria_id": "cat_fywrh23ssi",
    "marca": "Xiaomi",
    "precio": {
      "valor": 1210.16,
      "moneda": "COP"
    },
    "stock": 185,
    "descripcion": "Sabor tradicional colombiano y frescura garantizada. Perfecto para regalo o colección.",
    "especificaciones": {
      "color": "azul",
      "talla": "XS",
      "peso_kg": 0.41
    },
    "imagenes": [
      "https://img.ejemplo.com/img_hzx0q2.jpg"
    ],
    "rating_promedio": 5.0,
    "num_resenas": 1,
    "tags": [
      "eco",
      "importado"
    ],
    "fecha_creacion": "2023-07-04",
    "activo": true
  },
  {
    "_id": "prd_ng9t32a00w",
    "nombre": "Juguete para perro resistente 330",
    "categoria_id": "cat_ck4xbio5xf",
    "marca": "Genérica",
    "precio": {
      "valor": 635.3,
      "moneda": "COP"
    },
    "stock": 167,
    "descripcion": "Envío rápido y empaque seguro. Perfecto para regalo o colección.",
    "especificaciones": {
      "color": "negro",
      "talla": "XL",
      "peso_kg": 1.61
    },
    "imagenes": [
      "https://img.ejemplo.com/img_vgmr12.jpg",
      "https://img.ejemplo.com/img_c3aqbd.jpg"
    ],
    "rating_promedio": 5.0,
    "num_resenas": 1,
    "tags": [
      "importado",
      "oferta"
    ],
    "fecha_creacion": "2023-01-16",
    "activo": true
  },
  {
    "_id": "prd_tmf1chra4h",
    "nombre": "Rompecabezas 1000 piezas 473",
    "categoria_id": "cat_hvuwggm7mv",
    "marca": "Hasbro",
    "precio": {
      "valor": 652.91,
      "moneda": "COP"
    },
    "stock": 424,
    "descripcion": "Artesanía hecha a mano por comunidades locales. Material resistente y acabado premium.",
    "especificaciones": {
      "color": "gris",
      "talla": "M",
      "peso_kg": 3.68
    },
    "imagenes": [
      "https://img.ejemplo.com/img_ojisc1.jpg"
    ],
    "rating_promedio": 4.0,
    "num_resenas": 1,
    "tags": [
      "importado",
      "oferta",
      "premium"
    ],
    "fecha_creacion": "2023-11-01",
    "activo": true
  },
  {
    "_id": "prd_8jwffuifo2",
    "nombre": "Zapatillas running 780",
    "categoria_id": "cat_a7pf17yp91",
    "marca": "Adidas",
    "precio": {
      "valor": 290.6,
      "moneda": "COP"
    },
    "stock": 224,
    "descripcion": "Disponible en varias tallas y colores. Material resistente y acabado premium.",
    "especificaciones": {
      "color": "rojo",
      "talla": "L",
      "peso_kg": 1.19
    },
    "imagenes": [
      "https://img.ejemplo.com/img_yaly8s.jpg",
      "https://img.ejemplo.com/img_yice90.jpg",
      "https://img.ejemplo.com/img_112to7.jpg"
    ],
    "rating_promedio": 0.0,
    "num_resenas": 0,
    "tags": [
      "oferta",
      "nuevo"
    ],
    "fecha_creacion": "2025-04-06",
    "activo": true
  },
  {
    "_id": "prd_vyj4j7v3zg",
    "nombre": "Smartwatch deportivo 835",
    "categoria_id": "cat_fywrh23ssi",
    "marca": "Xiaomi",
    "precio": {
      "valor": 48.88,
      "moneda": "COP"
    },
    "stock": 343,
    "descripcion": "Sabor tradicional colombiano y frescura garantizada. Ideal para uso diario y recomendado por compradores.",
    "especificaciones": {
      "color": "azul",
      "talla": "S",
      "peso_kg": 4.35
    },
    "imagenes": [
      "https://img.ejemplo.com/img_6j59y2.jpg",
      "https://img.ejemplo.com/img_hwe901.jpg",
      "https://img.ejemplo.com/img_7q93xv.jpg"
    ],
    "rating_promedio": 4.5,
    "num_resenas": 2,
    "tags": [
      "nuevo"
    ],
    "fecha_creacion": "2024-11-02",
    "activo": false
  },
  {
    "_id": "prd_n4i9ue135k",
    "nombre": "Rompecabezas 1000 piezas 392",
    "categoria_id": "cat_hvuwggm7mv",
    "marca": "Hasbro",
    "precio": {
      "valor": 1000.36,
      "moneda": "COP"
    },
    "stock": 214,
    "descripcion": "Disponible en varias tallas y colores. Artesanía hecha a mano por comunidades locales.",
    "especificaciones": {
      "color": "blanco",
      "talla": "M",
      "peso_kg": 0.15
    },
    "imagenes": [
      "https://img.ejemplo.com/img_g750bj.jpg",
      "https://img.ejemplo.com/img_8r9cbb.jpg"
    ],
    "rating_promedio": 5.0,
    "num_resenas": 1,
    "tags": [
      "premium",
      "eco"
    ],
    "fecha_creacion": "2023-01-29",
    "activo": true
  },
  {
    "_id": "prd_khjxlwq440",
    "nombre": "Portátil 14'' i5 16GB 259",
    "categoria_id": "cat_ig7gpfbsxi",
    "marca": "Lenovo",
    "precio": {
      "valor": 247.52,
      "moneda": "COP"
    },
    "stock": 176,
    "descripcion": "Disponible en varias tallas y colores. Sabor tradicional colombiano y frescura garantizada.",
    "especificaciones": {
      "color": "blanco",
      "talla": "XS",
      "peso_kg": 3.6
    },
    "imagenes": [
      "https://img.ejemplo.com/img_cyaz6z.jpg",
      "https://img.ejemplo.com/img_d547hs.jpg",
      "https://img.ejemplo.com/img_avyrcm.jpg"
    ],
    "rating_promedio": 5.0,
    "num_resenas": 2,
    "tags": [
      "eco"
    ],
    "fecha_creacion": "2021-09-06",
    "activo": true
  },
  {
    "_id": "prd_esw5qy8dyp",
    "nombre": "Smartwatch deportivo 802",
    "categoria_id": "cat_fywrh23ssi",
    "marca": "Huawei",
    "precio": {
      "valor": 579.23,
      "moneda": "COP"
    },
    "stock": 146,
    "descripcion": "Producto original con excelente calidad. Ideal para uso diario y recomendado por compradores.",
    "especificaciones": {
      "color": "azul",
      "talla": "XL",
      "peso_kg": 2.41
    },
    "imagenes": [
      "https://img.ejemplo.com/img_j02aoe.jpg",
      "https://img.ejemplo.com/img_zlobrz.jpg",
      "https://img.ejemplo.com/img_3b1y9b.jpg"
    ],
    "rating_promedio": 5.0,
    "num_resenas": 1,
    "tags": [
      "importado"
    ],
    "fecha_creacion": "2023-06-15",
    "activo": true
  },
  {
    "_id": "prd_jdhntu8vei",
    "nombre": "Smartwatch deportivo 387",
    "categoria_id": "cat_fywrh23ssi",
    "marca": "Samsung",
    "precio": {
      "valor": 1556.47,
      "moneda": "COP"
    },
    "stock": 174,
    "descripcion": "Sabor tradicional colombiano y frescura garantizada. Artesanía hecha a mano por comunidades locales.",
    "especificaciones": {
      "color": "negro",
      "talla": "XL",
      "peso_kg": 3.39
    },
    "imagenes": [
      "https://img.ejemplo.com/img_o2iu1j.jpg"
    ],
    "rating_promedio": 4.0,
    "num_resenas": 1,
    "tags": [
      "eco",
      "oferta",
      "nuevo"
    ],
    "fecha_creacion": "2023-06-18",
    "activo": true
  },
  {
    "_id": "prd_sb1j1yz6bq",
    "nombre": "Portátil 14'' i5 16GB 443",
    "categoria_id": "cat_ig7gpfbsxi",
    "marca": "Asus",
    "precio": {
      "valor": 1337.71,
      "moneda": "COP"
    },
    "stock": 209,
    "descripcion": "Ideal para uso diario y recomendado por compradores. Sabor tradicional colombiano y frescura garantizada.",
    "especificaciones": {
      "color": "gris",
      "talla": "M",
      "peso_kg": 1.56
    },
    "imagenes": [
      "https://img.ejemplo.com/img_kz2p4e.jpg",
      "https://img.ejemplo.com/img_pfndc7.jpg",
      "https://img.ejemplo.com/img_ctyj9b.jpg"
    ],
    "rating_promedio": 5.0,
    "num_resenas": 1,
    "tags": [
      "nuevo",
      "importado",
      "oferta"
    ],
    "fecha_creacion": "2025-07-18",
    "activo": true
  },
  {
    "_id": "prd_axddpc7zoh",
    "nombre": "Crema hidratante corporal 556",
    "categoria_id": "cat_9cuunmftk8",
    "marca": "Neutrogena",
    "precio": {
      "valor": 1675.42,
      "moneda": "COP"
    },
    "stock": 450,
    "descripcion": "Disponible en varias tallas y colores. Sabor tradicional colombiano y frescura garantizada.",
    "especificaciones": {
      "color": "verde",
      "talla": "L",
      "peso_kg": 3.29
    },
    "imagenes": [
      "https://img.ejemplo.com/img_ocunsw.jpg",
      "https://img.ejemplo.com/img_929cb1.jpg"
    ],
    "rating_promedio": 0.0,
    "num_resenas": 0,
    "tags": [
      "eco",
      "nuevo"
    ],
    "fecha_creacion": "2024-08-29",
    "activo": true
  },
  {
    "_id": "prd_ssuyajwiyk",
    "nombre": "Zapatillas running 543",
    "categoria_id": "cat_a7pf17yp91",
    "marca": "Puma",
    "precio": {
      "valor": 1088.62,
      "moneda": "COP"
    },
    "stock": 408,
    "descripcion": "Ideal para uso diario y recomendado por compradores. Material resistente y acabado premium.",
    "especificaciones": {
      "color": "azul",
      "talla": "XL",
      "peso_kg": 1.82
    },
    "imagenes": [
      "https://img.ejemplo.com/img_0mhqsx.jpg",
      "https://img.ejemplo.com/img_iq3b56.jpg"
    ],
    "rating_promedio": 5.0,
    "num_resenas": 1,
    "tags": [
      "oferta",
      "popular",
      "premium"
    ],
    "fecha_creacion": "2024-02-02",
    "activo": true
  },
  {
    "_id": "prd_7v7dmoudzp",
    "nombre": "Juguete para perro resistente 106",
    "categoria_id": "cat_ck4xbio5xf",
    "marca": "Kong",
    "precio": {
      "valor": 859.14,
      "moneda": "COP"
    },
    "stock": 416,
    "descripcion": "Envío rápido y empaque seguro. Perfecto para regalo o colección.",
    "especificaciones": {
      "color": "rojo",
      "talla": "L",
      "peso_kg": 4.19
    },
    "imagenes": [
      "https://img.ejemplo.com/img_c6dgkc.jpg"
    ],
    "rating_promedio": 0.0,
    "num_resenas": 0,
    "tags": [
      "importado",
      "eco",
      "premium"
    ],
    "fecha_creacion": "2024-03-16",
    "activo": true
  },
  {
    "_id": "prd_k33e7rkoyi",
    "nombre": "Rompecabezas 1000 piezas 622",
    "categoria_id": "cat_hvuwggm7mv",
    "marca": "Mattel",
    "precio": {
      "valor": 539.12,
      "moneda": "COP"
    },
    "stock": 113,
    "descripcion": "Perfecto para regalo o colección. Artesanía hecha a mano por comunidades locales.",
    "especificaciones": {
      "color": "negro",
      "talla": "L",
      "peso_kg": 4.77
    },
    "imagenes": [
      "https://img.ejemplo.com/img_3mjleh.jpg"
    ],
    "rating_promedio": 4.7,
    "num_resenas": 3,
    "tags": [
      "oferta"
    ],
    "fecha_creacion": "2025-09-25",
    "activo": true
  },
  {
    "_id": "prd_jilkuudxy1",
    "nombre": "Mouse inalámbrico 227",
    "categoria_id": "cat_ig7gpfbsxi",
    "marca": "Microsoft",
    "precio": {
      "valor": 1526.94,
      "moneda": "COP"
    },
    "stock": 495,
    "descripcion": "Envío rápido y empaque seguro. Ideal para uso diario y recomendado por compradores.",
    "especificaciones": {
      "color": "blanco",
      "talla": "XL",
      "peso_kg": 0.5
    },
    "imagenes": [
      "https://img.ejemplo.com/img_e8v5gg.jpg"
    ],
    "rating_promedio": 5.0,
    "num_resenas": 1,
    "tags": [
      "eco"
    ],
    "fecha_creacion": "2021-05-01",
    "activo": true
  },
  {
    "_id": "prd_ie9jkz2w3x",
    "nombre": "Smartwatch deportivo 588",
    "categoria_id": "cat_fywrh23ssi",
    "marca": "Huawei",
    "precio": {
      "valor": 1263.68,
      "moneda": "COP"
    },
    "stock": 297,
    "descripcion": "Sabor tradicional colombiano y frescura garantizada. Producto original con excelente calidad.",
    "especificaciones": {
      "color": "azul",
      "talla": "L",
      "peso_kg": 4.84
    },
    "imagenes": [
      "https://img.ejemplo.com/img_fr1534.jpg"
    ],
    "rating_promedio": 5.0,
    "num_resenas": 3,
    "tags": [
      "nuevo"
    ],
    "fecha_creacion": "2023-09-02",
    "activo": true
  },
  {
    "_id": "prd_tkjza5u9qy",
    "nombre": "Juguete para perro resistente 550",
    "categoria_id": "cat_ck4xbio5xf",
    "marca": "Genérica",
    "precio": {
      "valor": 301.11,
      "moneda": "COP"
    },
    "stock": 277,
    "descripcion": "Ideal para uso diario y recomendado por compradores. Material resistente y acabado premium.",
    "especificaciones": {
      "color": "gris",
      "talla": "L",
      "peso_kg": 2.24
    },
    "imagenes": [
      "https://img.ejemplo.com/img_yrrvof.jpg",
      "https://img.ejemplo.com/img_ftnlfz.jpg"
    ],
    "rating_promedio": 1.0,
    "num_resenas": 1,
    "tags": [
      "premium"
    ],
    "fecha_creacion": "2023-11-17",
    "activo": true
  },
  {
    "_id": "prd_ics36y27m9",
    "nombre": "Mouse inalámbrico 497",
    "categoria_id": "cat_ig7gpfbsxi",
    "marca": "Genius",
    "precio": {
      "valor": 992.4,
      "moneda": "COP"
    },
    "stock": 42,
    "descripcion": "Artesanía hecha a mano por comunidades locales. Envío rápido y empaque seguro.",
    "especificaciones": {
      "color": "azul",
      "talla": "M",
      "peso_kg": 4.38
    },
    "imagenes": [
      "https://img.ejemplo.com/img_xpnfkt.jpg",
      "https://img.ejemplo.com/img_lhlbhb.jpg",
      "https://img.ejemplo.com/img_cs1xo8.jpg"
    ],
    "rating_promedio": 0.0,
    "num_resenas": 0,
    "tags": [
      "oferta"
    ],
    "fecha_creacion": "2025-08-07",
    "activo": true
  },
  {
    "_id": "prd_pzuzk8lwkx",
    "nombre": "Mouse inalámbrico 150",
    "categoria_id": "cat_ig7gpfbsxi",
    "marca": "Microsoft",
    "precio": {
      "valor": 564.57,
      "moneda": "COP"
    },
    "stock": 10,
    "descripcion": "Artesanía hecha a mano por comunidades locales. Perfecto para regalo o colección.",
    "especificaciones": {
      "color": "gris",
      "talla": "XS",
      "peso_kg": 4.8
    },
    "imagenes": [
      "https://img.ejemplo.com/img_ftrpk3.jpg",
      "https://img.ejemplo.com/img_rbkmt7.jpg"
    ],
    "rating_promedio": 5.0,
    "num_resenas": 1,
    "tags": [
      "importado"
    ],
    "fecha_creacion": "2022-12-24",
    "activo": true
  },
  {
    "_id": "prd_5c42q8fs5m",
    "nombre": "Crema hidratante corporal 622",
    "categoria_id": "cat_9cuunmftk8",
    "marca": "Neutrogena",
    "precio": {
      "valor": 803.87,
      "moneda": "COP"
    },
    "stock": 269,
    "descripcion": "Material resistente y acabado premium. Artesanía hecha a mano por comunidades locales.",
    "especificaciones": {
      "color": "gris",
      "talla": "XL",
      "peso_kg": 0.76
    },
    "imagenes": [
      "https://img.ejemplo.com/img_ko9qyy.jpg"
    ],
    "rating_promedio": 5.0,
    "num_resenas": 3,
    "tags": [
      "eco",
      "premium",
      "nuevo"
    ],
    "fecha_creacion": "2024-05-01",
    "activo": true
  },
  {
    "_id": "prd_gi7ztccc9h",
    "nombre": "Zapatillas running 653",
    "categoria_id": "cat_a7pf17yp91",
    "marca": "Adidas",
    "precio": {
      "valor": 24.16,
      "moneda": "COP"
    },
    "stock": 0,
    "descripcion": "Envío rápido y empaque seguro. Sabor tradicional colombiano y frescura garantizada.",
    "especificaciones": {
      "color": "blanco",
      "talla": "L",
      "peso_kg": 4.72
    },
    "imagenes": [
      "https://img.ejemplo.com/img_e3xc6e.jpg",
      "https://img.ejemplo.com/img_7nrgpi.jpg",
      "https://img.ejemplo.com/img_1ix5yg.jpg"
    ],
    "rating_promedio": 4.0,
    "num_resenas": 1,
    "tags": [
      "popular",
      "eco",
      "importado"
    ],
    "fecha_creacion": "2022-04-19",
    "activo": true
  },
  {
    "_id": "prd_sj3530yr2m",
    "nombre": "Rompecabezas 1000 piezas 698",
    "categoria_id": "cat_hvuwggm7mv",
    "marca": "Ravensburger",
    "precio": {
      "valor": 896.24,
      "moneda": "COP"
    },
    "stock": 0,
    "descripcion": "Perfecto para regalo o colección. Material resistente y acabado premium.",
    "especificaciones": {
      "color": "blanco",
      "talla": "S",
      "peso_kg": 3.81
    },
    "imagenes": [
      "https://img.ejemplo.com/img_ns0mcy.jpg",
      "https://img.ejemplo.com/img_k771fm.jpg"
    ],
    "rating_promedio": 4.7,
    "num_resenas": 3,
    "tags": [
      "oferta",
      "popular",
      "nuevo"
    ],
    "fecha_creacion": "2025-09-18",
    "activo": true
  }
]